ts_python_client/__init__.py
ts_python_client/cli.py
ts_python_client/client.py
ts_python_client/commands/ScanCommand.py
ts_python_client/commands/UploadCommand.py
ts_python_client/commands/__init__.py
ts_python_client-2.0.6.dist-info/LICENSE
ts_python_client-2.0.6.dist-info/METADATA
ts_python_client-2.0.6.dist-info/WHEEL
ts_python_client-2.0.6.dist-info/top_level.txt
ts_python_client-2.0.6.dist-info/RECORD
