Metadata-Version: 2.1
Name: ts-python-client
Version: 2.0.6
Summary: A python client for TrustSource (https://app.trustsource.io) to manage open source code compliance
Home-page: https://github.com/trustsource/ts-python-client.git
Download-URL: 
Author: EACG GmbH
License: Apache-2.0
Keywords: scanning,dependencies,modules,TrustSource
Requires-Python: >=3.8
License-File: LICENSE
Requires-Dist: requests
Requires-Dist: click==8.1.3
Requires-Dist: click-params
